envpool.libs/libharfbuzz-c511b294.so.0.10000.1
envpool.libs/libQt5Core-9115a98e.so.5.5.1
envpool.libs/libpng12-0e256d12.so.0.54.0
envpool.libs/libicudata-631f3d9f.so.55.1
envpool.libs/libicuuc-63f32187.so.55.1
envpool.libs/libpcre16-aec9040d.so.3.13.2
envpool.libs/libgraphite2-318f96fd.so.3.0.1
envpool.libs/libicui18n-cbe97bde.so.55.1
envpool.libs/libQt5Gui-cba8e061.so.5.5.1
envpool.libs/libfreetype-47a43bfd.so.6.12.1
envpool/__init__.py
envpool/registration.py
envpool/entry.py
envpool/python/dm_envpool.py
envpool/python/protocol.py
envpool/python/gym_envpool.py
envpool/python/env_spec.py
envpool/python/__init__.py
envpool/python/gymnasium_envpool.py
envpool/python/data.py
envpool/python/envpool.py
envpool/python/lax.py
envpool/python/xla_template.py
envpool/python/api.py
envpool/python/utils.py
envpool/mujoco/libmujoco.so.2.2.1
envpool/mujoco/__init__.py
envpool/mujoco/mujoco_gym_envpool.so
envpool/mujoco/mujoco_dmc_envpool.so
envpool/mujoco/dmc/__init__.py
envpool/mujoco/dmc/registration.py
envpool/mujoco/assets_dmc/reacher.xml
envpool/mujoco/assets_dmc/stacker.xml
envpool/mujoco/assets_dmc/manipulator.xml
envpool/mujoco/assets_dmc/hopper.xml
envpool/mujoco/assets_dmc/cheetah.xml
envpool/mujoco/assets_dmc/ball_in_cup.xml
envpool/mujoco/assets_dmc/walker.xml
envpool/mujoco/assets_dmc/cartpole.xml
envpool/mujoco/assets_dmc/dog.xml
envpool/mujoco/assets_dmc/humanoid_CMU.xml
envpool/mujoco/assets_dmc/quadruped.xml
envpool/mujoco/assets_dmc/swimmer.xml
envpool/mujoco/assets_dmc/lqr.xml
envpool/mujoco/assets_dmc/finger.xml
envpool/mujoco/assets_dmc/fish.xml
envpool/mujoco/assets_dmc/acrobot.xml
envpool/mujoco/assets_dmc/point_mass.xml
envpool/mujoco/assets_dmc/pendulum.xml
envpool/mujoco/assets_dmc/humanoid.xml
envpool/mujoco/assets_dmc/common/skybox.xml
envpool/mujoco/assets_dmc/common/materials.xml
envpool/mujoco/assets_dmc/common/visual.xml
envpool/mujoco/gym/__init__.py
envpool/mujoco/gym/registration.py
envpool-0.8.4.dist-info/WHEEL
envpool-0.8.4.dist-info/METADATA
envpool-0.8.4.dist-info/RECORD
envpool-0.8.4.dist-info/top_level.txt
