Metadata-Version: 2.1
Name: envpool
Version: 0.8.4
Summary: "C++-based high-performance parallel environment execution engine (vectorized env) for general RL environments."
Home-page: https://github.com/sail-sg/envpool
Author: "EnvPool Contributors"
Author-email: "sail@sea.com"
Project-URL: Bug Tracker, https://github.com/sail-sg/envpool/issues
Classifier: Programming Language :: Python :: 3
Classifier: Programming Language :: Python :: 3.7
Classifier: Programming Language :: Python :: 3.8
Classifier: Programming Language :: Python :: 3.9
Classifier: Programming Language :: Python :: 3.10
Classifier: Programming Language :: Python :: 3.11
Classifier: License :: OSI Approved :: Apache Software License
Classifier: Operating System :: POSIX :: Linux
Classifier: Topic :: Scientific/Engineering :: Artificial Intelligence
Requires-Python: >=3.7
Requires-Dist: dm-env >=1.4
Requires-Dist: gym >=0.18
Requires-Dist: gymnasium >=0.26
Requires-Dist: numpy >=1.19
Requires-Dist: types-protobuf >=3.17.3
Requires-Dist: typing-extensions
Requires-Dist: packaging
Requires-Dist: optree >=0.6.0
